{"title":{"a":"Lista/Pacto","b":"Partido","c":"Votos","d":"Porcentaje","e":"Candidatos","f":"Electo","sd":null},"isVisible":{"a":"true","b":"true","c":"true","d":"true","e":"false","f":"true","sd":null},"dataType":{"a":"String","b":"String","c":"Integer","d":"Integer","e":"Integer","f":"Integer","sd":null},"data":[{"a":"G. FRENTE AMPLIO","b":null,"c":"684","d":"9,55%","e":"6","f":"","sd":[{"a":"PARTIDO HUMANISTA","b":null,"c":"684","d":"9,55%","e":null,"f":null,"sd":[{"a":"10. JUAN ORTIZ SOTO","b":"PH","c":"66","d":"0,92%","e":null,"f":"","sd":null},{"a":"11. AUCAN HUILCAMAN PAILLAMA","b":"IND-PH","c":"209","d":"2,92%","e":null,"f":"","sd":null},{"a":"12. DIEGO ALEXIS ANCALAO GAVILAN","b":"IND-PH","c":"249","d":"3,48%","e":null,"f":"","sd":null},{"a":"13. GABRIELA PAZ MELENDEZ TORMEN","b":"PH","c":"59","d":"0,82%","e":null,"f":"","sd":null},{"a":"14. GLORIA MUJICA ASCUI","b":"PH","c":"46","d":"0,64%","e":null,"f":"","sd":null},{"a":"15. LUCIA CECILIA TORMEN MENDEZ","b":"PH","c":"55","d":"0,77%","e":null,"f":"","sd":null}]}]},{"a":"H. SUMEMOS","b":null,"c":"205","d":"2,86%","e":"4","f":"","sd":[{"a":"AMPLITUD","b":null,"c":"205","d":"2,86%","e":null,"f":null,"sd":[{"a":"16. EDUARDO DIAZ HERRERA","b":"AMPLI.","c":"94","d":"1,31%","e":null,"f":"","sd":null},{"a":"17. EMA  VIDAL DIAZ","b":"AMPLI.","c":"51","d":"0,71%","e":null,"f":"","sd":null},{"a":"18. TATIANA  RUDOLPH ESPINOZA","b":"AMPLI.","c":"37","d":"0,52%","e":null,"f":"","sd":null},{"a":"19. JUAN EDILBERTO RAMIREZ VILLAGRA","b":"AMPLI.","c":"23","d":"0,32%","e":null,"f":"","sd":null}]}]},{"a":"N. LA FUERZA DE LA MAYORIA","b":null,"c":"2.274","d":"31,74%","e":"5","f":"","sd":[{"a":"PARTIDO POR LA DEMOCRACIA","b":null,"c":"2.173","d":"30,33%","e":null,"f":null,"sd":[{"a":"20. JAIME QUINTANA LEAL","b":"PPD","c":"1.990","d":"27,78%","e":null,"f":"*","sd":null},{"a":"21. ALBERTO ANTONIO PIZARRO CHAÑILAO","b":"PPD","c":"73","d":"1,02%","e":null,"f":"","sd":null},{"a":"22. CLAUDIA ANDREA PALMA NUÑEZ","b":"PPD","c":"110","d":"1,54%","e":null,"f":"","sd":null}]},{"a":"PARTIDO COMUNISTA DE CHILE","b":null,"c":"41","d":"0,57%","e":null,"f":null,"sd":[{"a":"23. PATRICIA DEL CARMEN COÑOMAN CARRILLO","b":"PCCH","c":"41","d":"0,57%","e":null,"f":"","sd":null}]},{"a":"PARTIDO SOCIALISTA DE CHILE","b":null,"c":"60","d":"0,84%","e":null,"f":null,"sd":[{"a":"24. FLOR  DOMINGUEZ ROSAS","b":"PSCH","c":"60","d":"0,84%","e":null,"f":"","sd":null}]}]},{"a":"O. CONVERGENCIA DEMOCRATICA","b":null,"c":"888","d":"12,40%","e":"2","f":"","sd":[{"a":"PARTIDO DEMOCRATA CRISTIANO","b":null,"c":"888","d":"12,40%","e":null,"f":null,"sd":[{"a":"25. FUAD EDUARDO CHAHIN VALENZUELA","b":"PDC","c":"418","d":"5,83%","e":null,"f":"","sd":null},{"a":"26. FRANCISCO  HUENCHUMILLA JARAMILLO","b":"PDC","c":"470","d":"6,56%","e":null,"f":"*","sd":null}]}]},{"a":"P. CHILE VAMOS","b":null,"c":"2.721","d":"37,98%","e":"6","f":"","sd":[{"a":"EVOLUCION POLITICA","b":null,"c":"1.696","d":"23,67%","e":null,"f":null,"sd":[{"a":"27. FELIPE KAST SOMMERHOFF","b":"EVOP.","c":"1.173","d":"16,37%","e":null,"f":"*","sd":null},{"a":"28. CARMEN GLORIA ARAVENA ACUÑA","b":"EVOP.","c":"523","d":"7,30%","e":null,"f":"*","sd":null}]},{"a":"RENOVACION NACIONAL","b":null,"c":"738","d":"10,30%","e":null,"f":null,"sd":[{"a":"29. JOSE GARCIA RUMINOT","b":"RN","c":"312","d":"4,36%","e":null,"f":"*","sd":null},{"a":"30. GERMAN BECKER ALVEAR","b":"RN","c":"426","d":"5,95%","e":null,"f":"","sd":null}]},{"a":"UNION DEMOCRATA INDEPENDIENTE","b":null,"c":"287","d":"4,01%","e":null,"f":null,"sd":[{"a":"31. JOSE VILLAGRAN SANDOVAL","b":"UDI","c":"56","d":"0,78%","e":null,"f":"","sd":null},{"a":"32. GUSTAVO HASBUN SELUME","b":"UDI","c":"231","d":"3,22%","e":null,"f":"","sd":null}]}]},{"a":"CANDIDATURA INDEPENDIENTE","b":null,"c":"392","d":"5,47%","e":null,"f":null,"sd":[{"a":"33. ROJO EDWARDS SILVA","b":"IND","c":"392","d":"5,47%","e":null,"f":"","sd":null}]}],"resumen":[{"a":"Válidamente Emitidos","b":null,"c":"7.164","d":"87,24%","e":null,"f":null,"sd":null},{"a":"Votos Nulos","b":null,"c":"365","d":"4,44%","e":null,"f":null,"sd":null},{"a":"Votos en Blanco","b":null,"c":"683","d":"8,32%","e":null,"f":null,"sd":null},{"a":"Total Votación","b":null,"c":"8.212","d":"100,00%","e":null,"f":null,"sd":null}],"colegioEscrutador":null,"labels":"5","mesasEscrutadas":"58","totalMesas":"58","totalMesasPorcent":"100,00%","tipoGlosaComputo":"1","mostrarGlosaNominados":true,"tipoGlosaNominados":null}