{"title":{"a":"Nombre de los Candidatos","b":"Partido","c":"Votos","d":"Porcentaje","e":"Candidatos","f":"Electo","sd":null},"isVisible":{"a":"true","b":"false","c":"true","d":"true","e":"false","f":"true","sd":null},"dataType":{"a":"String","b":"String","c":"Integer","d":"Integer","e":"Integer","f":"Integer","sd":null},"data":[{"a":"3. SEBASTIAN PIÑERA ECHENIQUE","b":null,"c":"1.681","d":"51,22%","e":null,"f":"*","sd":null},{"a":"4. ALEJANDRO  GUILLIER ALVAREZ","b":null,"c":"1.601","d":"48,78%","e":null,"f":"","sd":null}],"resumen":[{"a":"Válidamente Emitidos","b":null,"c":"3.282","d":"99,12%","e":null,"f":null,"sd":null},{"a":"Votos Nulos","b":null,"c":"24","d":"0,72%","e":null,"f":null,"sd":null},{"a":"Votos en Blanco","b":null,"c":"5","d":"0,15%","e":null,"f":null,"sd":null},{"a":"Total Votación","b":null,"c":"3.311","d":"100,00%","e":null,"f":null,"sd":null}],"colegioEscrutador":null,"labels":null,"mesasEscrutadas":"19","totalMesas":"19","totalMesasPorcent":"100,00%","tipoGlosaComputo":"1","mostrarGlosaNominados":true,"tipoGlosaNominados":"1"}