{"title":{"a":"Circ. Electoral","b":"Total Mesas","c":"Total Electores","d":"Total Votación","e":"% Participación"},"isVisible":{"a":"true","b":"true","c":"true","d":"true","e":"true"},"dataType":{"a":"String","b":"Integer","c":"Integer","d":"Integer","e":"Integer"},"data":[{"a":"OSORNO","b":"372","c":"121.282","d":"56.295","e":"46,42"},{"a":"RAHUE","b":"42","c":"12.518","d":"4.924","e":"39,34"},{"a":"RAHUE SUR","b":"19","c":"6.280","d":"2.718","e":"43,28"}],"resumen":[{"a":"TOTAL","b":"433","c":"140.080","d":"63.937","e":"45,64"}],"marca":null}