{"title":{"a":"Circ. Electoral","b":"Total Mesas","c":"Total Electores","d":"Total Votación","e":"% Participación"},"isVisible":{"a":"true","b":"true","c":"true","d":"true","e":"true"},"dataType":{"a":"String","b":"Integer","c":"Integer","d":"Integer","e":"Integer"},"data":[{"a":"COCHAMO","b":"9","c":"2.597","d":"650","e":"25,03"},{"a":"LLANADA GRANDE","b":"2","c":"530","d":"188","e":"35,47"},{"a":"PUELO","b":"4","c":"1.311","d":"640","e":"48,82"}],"resumen":[{"a":"TOTAL","b":"15","c":"4.438","d":"1.478","e":"33,30"}],"marca":null}