{"title":{"a":"Circ. Electoral","b":"Total Mesas","c":"Total Electores","d":"Total Votación","e":"% Participación"},"isVisible":{"a":"true","b":"true","c":"true","d":"true","e":"true"},"dataType":{"a":"String","b":"Integer","c":"Integer","d":"Integer","e":"Integer"},"data":[{"a":"ESTACION LO ESPEJO","b":"132","c":"43.434","d":"19.126","e":"44,03"},{"a":"LO VALLEDOR","b":"161","c":"49.841","d":"20.479","e":"41,09"}],"resumen":[{"a":"TOTAL","b":"293","c":"93.275","d":"39.605","e":"42,46"}],"marca":null}